vectorstore/__init__.py
vectorstore/_constants.py
vectorstore/_distance_strategy.py
vectorstore/_index.py
vectorstore/delete_protection.py
vectorstore/filter.py
vectorstore/index_interface.py
vectorstore/index_list.py
vectorstore/index_model.py
vectorstore/match.py
vectorstore/metric.py
vectorstore/stats.py
vectorstore/vector.py
vectorstore/vectordb.py
singlestore_vectorstore-0.1.2.dist-info/LICENSE
singlestore_vectorstore-0.1.2.dist-info/METADATA
singlestore_vectorstore-0.1.2.dist-info/WHEEL
singlestore_vectorstore-0.1.2.dist-info/RECORD
