Metadata-Version: 2.3
Name: singlestore-vectorstore
Version: 0.1.2
Summary: Vector store interface for SingleStore Database
License: Apache License (2.0)
Author: Volodymyr Tkachuk
Author-email: vtkachuk-ua@singlestore.com
Requires-Python: >=3.9,<4.0
Classifier: License :: Other/Proprietary License
Classifier: Programming Language :: Python :: 3
Classifier: Programming Language :: Python :: 3.9
Classifier: Programming Language :: Python :: 3.10
Classifier: Programming Language :: Python :: 3.11
Classifier: Programming Language :: Python :: 3.12
Classifier: Programming Language :: Python :: 3.13
Requires-Dist: singlestoredb (>=1.13.0,<2.0.0)
Requires-Dist: sqlalchemy (>=2.0.40,<3.0.0)
Project-URL: Homepage, https://github.com/singlestore-labs/vectorstore
Project-URL: Issues, https://github.com/singlestore-labs/vectorstore/issues
